{
  "date": "26.06.2026",
  "lastUpdated": "2026-06-27T17:48:20+03:00",
  "source": "TCMB · gold-api.com",
  "items": [
    {
      "code": "USD",
      "name": "Dolar",
      "symbol": "$",
      "buy": 46.4482,
      "sell": 46.5319
    },
    {
      "code": "EUR",
      "name": "Euro",
      "symbol": "€",
      "buy": 52.9289,
      "sell": 53.0242
    },
    {
      "code": "GBP",
      "name": "Sterlin",
      "symbol": "£",
      "buy": 61.2684,
      "sell": 61.5878
    },
    {
      "code": "GRAM_ALTIN",
      "name": "Gram Altın",
      "symbol": "gr",
      "buy": null,
      "sell": 6119.68
    }
  ]
}
